maboss_test/MaBoSSTestCase.py
maboss_test/__init__.py
maboss_test-1.0.0a4.dist-info/LICENSE
maboss_test-1.0.0a4.dist-info/METADATA
maboss_test-1.0.0a4.dist-info/WHEEL
maboss_test-1.0.0a4.dist-info/top_level.txt
maboss_test-1.0.0a4.dist-info/RECORD
